LICENSE
MANIFEST.in
README.rst
setup.py
curator/__init__.py
curator/admin.py
curator/forms.py
curator/models.py
curator/urls.py
curator/utils.py
curator/views.py
curator/media/.DS_Store
curator/media/css/global.css
curator/media/img/.DS_Store
curator/media/img/ajax-loader.gif
curator/media/js/.DS_Store
curator/media/js/global.js
curator/media/js/jquery.flot.js
curator/media/js/jquery.portal.min.js
curator/migrations/0001_initial.py
curator/migrations/__init__.py
curator/templates/admin/curator/dashboardwidget/change_form.html
curator/templates/curator/base.html
curator/templates/curator/dashboard.html
curator/templates/curator/widget.html
curator/templates/curator/widget_block_body.html
curator/templates/curator/widget_block_head.html
curator/templatetags/__init__.py
curator/templatetags/widget_tag.py
django_curator.egg-info/PKG-INFO
django_curator.egg-info/SOURCES.txt
django_curator.egg-info/dependency_links.txt
django_curator.egg-info/top_level.txt